megacrazyscripts/__init__.py
megacrazyscripts/converter.py
megacrazyscripts/mix_audio_image.py
megacrazyscripts/slowedreverb.py
megacrazyscripts/thumbnail_img.py
megacrazyscripts/video_img.py
megacrazyscripts/ytdw.py
megacrazyscripts-0.1.5.dist-info/LICENSE
megacrazyscripts-0.1.5.dist-info/METADATA
megacrazyscripts-0.1.5.dist-info/WHEEL
megacrazyscripts-0.1.5.dist-info/top_level.txt
megacrazyscripts-0.1.5.dist-info/RECORD
